coglet/__init__.py
coglet-0.0.1.dist-info/METADATA
coglet-0.0.1.dist-info/WHEEL
coglet-0.0.1.dist-info/RECORD
