Metadata-Version: 2.4
Name: coglet
Version: 0.0.1
Summary: Rust powered C2 for Cog
License: Apache-2.0
Requires-Python: >=3.10
